zumidashboard/README.md
zumidashboard/__init__.py
zumidashboard/app.py
zumidashboard/boot_calibration.py
zumidashboard/config.py
zumidashboard/drive_mode.py
zumidashboard/fullchain.pem
zumidashboard/gesture.py
zumidashboard/idle_animation.py
zumidashboard/privkey.pem
zumidashboard/scripts.py
zumidashboard/sounds.py
zumidashboard/updater.py
zumidashboard/utils.py
zumidashboard/webstreaming.py
zumidashboard/wpa_supplicant.conf
zumidashboard/crt/private.key
zumidashboard/crt/zumidashboard_ai.crt
zumidashboard/dashboard/LessonList.json
zumidashboard/dashboard/LessonList_with_competition.json
zumidashboard/dashboard/LessonList_with_lesson.json
zumidashboard/dashboard/LessonList_zh.json
zumidashboard/dashboard/NewLessonList.json
zumidashboard/dashboard/Ruler.pdf
zumidashboard/dashboard/asset-manifest.json
zumidashboard/dashboard/data.json
zumidashboard/dashboard/favicon.ico
zumidashboard/dashboard/index.html
zumidashboard/dashboard/log.txt
zumidashboard/dashboard/manifest.json
zumidashboard/dashboard/releasenotes.json
zumidashboard/dashboard/robots.txt
zumidashboard/dashboard/zumidashboard_en.json
zumidashboard/dashboard/zumidashboard_hu.json
zumidashboard/dashboard/zumidashboard_ko.json
zumidashboard/dashboard/zumidashboard_zh.json
zumidashboard/dashboard/css/bootstrap-grid.css
zumidashboard/dashboard/css/bootstrap-grid.css.map
zumidashboard/dashboard/css/bootstrap-grid.min.css
zumidashboard/dashboard/css/bootstrap-grid.min.css.map
zumidashboard/dashboard/css/bootstrap-reboot.css
zumidashboard/dashboard/css/bootstrap-reboot.css.map
zumidashboard/dashboard/css/bootstrap-reboot.min.css
zumidashboard/dashboard/css/bootstrap-reboot.min.css.map
zumidashboard/dashboard/css/bootstrap.css
zumidashboard/dashboard/css/bootstrap.css.map
zumidashboard/dashboard/css/bootstrap.min.css
zumidashboard/dashboard/css/bootstrap.min.css.map
zumidashboard/dashboard/css/stylesheet.css
zumidashboard/dashboard/css/fonts/Avenir-Book.ttf
zumidashboard/dashboard/css/fonts/Avenir-Book.woff
zumidashboard-2.92.dist-info/METADATA
zumidashboard-2.92.dist-info/WHEEL
zumidashboard-2.92.dist-info/top_level.txt
zumidashboard-2.92.dist-info/RECORD
